shadowCrypt-0.1.2.dist-info/METADATA
shadowCrypt-0.1.2.dist-info/WHEEL
shadow_crypt/__init__.py
shadow_crypt/shadow_crypt.cp313-win_amd64.pyd
shadowCrypt-0.1.2.dist-info/RECORD
