Metadata-Version: 2.3
Name: shadowCrypt
Version: 0.1.2
Classifier: Programming Language :: Rust
Classifier: Programming Language :: Python :: Implementation :: CPython
Classifier: Programming Language :: Python :: Implementation :: PyPy
Summary: A cryptographic library integrating Diffie-Hellman, Kyber, NTRU, ECDH and RSA for secure communication.
Author: Albert
License: MIT
Requires-Python: >=3.8
